twilight_autocomplete/__init__.py
twilight_autocomplete/model.py
twilight_autocomplete-1.0.3.dist-info/LICENSE
twilight_autocomplete-1.0.3.dist-info/METADATA
twilight_autocomplete-1.0.3.dist-info/WHEEL
twilight_autocomplete-1.0.3.dist-info/top_level.txt
twilight_autocomplete-1.0.3.dist-info/RECORD
