Metadata-Version: 2.1
Name: twilight-autocomplete
Version: 1.0.3
Summary: Autocomplete Package built using NLTK for the twilight messaging client
Home-page: UNKNOWN
Author: Avneh Singh Bhatia
Author-email: avnehb@gmail.com
License: UNKNOWN
Platform: UNKNOWN
Requires-Dist: nltk
